<Properties StartupConfiguration="{4E9CAB9D-3B97-453E-804E-1A54A50C0E11}|Default">
  <MonoDevelop.Ide.ItemProperties.dotnetApiToRedis PreferredExecutionTarget="MonoDevelop.Default" />
  <MonoDevelop.Ide.Workbench ActiveDocument="dotnetApiToRedis/Data/RedisDB.cs">
    <Files>
      <File FileName="dotnetApiToRedis/Controllers/ChatMessageController.cs" Line="51" Column="41" />
      <File FileName="dotnetApiToRedis/Startup.cs" Line="24" Column="52" />
      <File FileName="docker-compose.yml" Line="8" Column="46" />
      <File FileName="dotnetApiToRedis/appsettings.json" Line="1" Column="1" />
      <File FileName="dotnetApiToRedis/appsettings.Development.json" Line="1" Column="1" />
      <File FileName="dotnetApiToRedis/Data/RedisDB.cs" Line="67" Column="47" />
    </Files>
  </MonoDevelop.Ide.Workbench>
  <MonoDevelop.Ide.DebuggingService.PinnedWatches />
  <MonoDevelop.Ide.Workspace ActiveConfiguration="Debug" />
  <MonoDevelop.Ide.ItemProperties.docker-compose PreferredExecutionTarget="MonoDevelop.Default" />
  <MonoDevelop.Ide.DebuggingService.Breakpoints>
    <BreakpointStore />
  </MonoDevelop.Ide.DebuggingService.Breakpoints>
  <MultiItemStartupConfigurations />
</Properties>